kubeagi_core/evaluation/ragas_eval.py
kubeagi_core/qa_provider/__init__.py
kubeagi_core/qa_provider/base.py
kubeagi_core/qa_provider/openai.py
kubeagi_core/qa_provider/prompt.py
kubeagi_core/qa_provider/zhipuai.py
kubeagi_core-0.0.1.dist-info/METADATA
kubeagi_core-0.0.1.dist-info/WHEEL
kubeagi_core-0.0.1.dist-info/top_level.txt
kubeagi_core-0.0.1.dist-info/RECORD
