Metadata-Version: 2.1
Name: kubeagi_core
Version: 0.0.1
Project-URL: Homepage, https://github.com/kubeagi/core-library
Project-URL: Issues, https://github.com/kubeagi/core-library/issues
Classifier: Programming Language :: Python :: 3
Classifier: License :: OSI Approved :: MIT License
Classifier: Operating System :: OS Independent
Requires-Python: >=3.8
Requires-Dist: langchain ==0.0.354
Requires-Dist: ragas ==0.0.22
Requires-Dist: zhipuai ==1.0.7
Requires-Dist: kubernetes ==25.3.0
